db_contrib_tool/__init__.py
db_contrib_tool/cli.py
db_contrib_tool/clients/__init__.py
db_contrib_tool/clients/download_client.py
db_contrib_tool/clients/file_service.py
db_contrib_tool/clients/git_client.py
db_contrib_tool/clients/io_client.py
db_contrib_tool/clients/platform_details.py
db_contrib_tool/clients/resmoke_proxy.py
db_contrib_tool/config/setup_repro_env_config.yml
db_contrib_tool/config.py
db_contrib_tool/pyinstaller.py
db_contrib_tool/services/__init__.py
db_contrib_tool/services/evergreen_service.py
db_contrib_tool/services/git_service.py
db_contrib_tool/services/platform_service.py
db_contrib_tool/setup_mongot_repro_env/README.md
db_contrib_tool/setup_mongot_repro_env/__init__.py
db_contrib_tool/setup_mongot_repro_env/cli.py
db_contrib_tool/setup_repro_env/README.md
db_contrib_tool/setup_repro_env/__init__.py
db_contrib_tool/setup_repro_env/artifact_discovery_service.py
db_contrib_tool/setup_repro_env/cli.py
db_contrib_tool/setup_repro_env/download_service.py
db_contrib_tool/setup_repro_env/release_discovery_service.py
db_contrib_tool/setup_repro_env/release_models.py
db_contrib_tool/setup_repro_env/request_models.py
db_contrib_tool/setup_repro_env/setup_repro_env.py
db_contrib_tool/symbolizer/README.md
db_contrib_tool/symbolizer/__init__.py
db_contrib_tool/symbolizer/cli.py
db_contrib_tool/symbolizer/mongo_log_parser_service.py
db_contrib_tool/symbolizer/mongosymb.py
db_contrib_tool/usage_analytics.py
db_contrib_tool/utils/__init__.py
db_contrib_tool/utils/build_system_options.py
db_contrib_tool/utils/evergreen_conn.py
db_contrib_tool/utils/filesystem.py
db_contrib_tool/utils/oauth.py
db_contrib_tool-2.2.1.dist-info/METADATA
db_contrib_tool-2.2.1.dist-info/WHEEL
db_contrib_tool-2.2.1.dist-info/entry_points.txt
db_contrib_tool-2.2.1.dist-info/RECORD
