Metadata-Version: 2.1
Name: db-contrib-tool
Version: 2.2.1
Summary: The `db-contrib-tool` - MongoDB's tool for contributors.
Home-page: https://github.com/10gen/db-contrib-tool
Author: DevProd Correctness
Author-email: devprod-correctness-team@mongodb.com
Requires-Python: >=3.9,<3.13
Classifier: Programming Language :: Python :: 3
Classifier: Programming Language :: Python :: 3.9
Classifier: Programming Language :: Python :: 3.10
Classifier: Programming Language :: Python :: 3.11
Requires-Dist: Inject (>=4.3.1,<5.0.0)
Requires-Dist: PyGithub (==1.58.0)
Requires-Dist: PyYAML (>=6.0.1,<7.0.0)
Requires-Dist: boto3 (>=1.34.156,<2.0.0)
Requires-Dist: botocore (>=1.34.156,<2.0.0)
Requires-Dist: click (>=8.1.3,<9.0.0)
Requires-Dist: distro (>=1.6.0,<2.0.0)
Requires-Dist: evergreen-py (>=3.14.0,<4.0.0)
Requires-Dist: gitpython (>=3.1.44,<4.0.0)
Requires-Dist: oauthlib (>=3.1.1,<4.0.0)
Requires-Dist: opentelemetry-api
Requires-Dist: opentelemetry-exporter-otlp-proto-grpc ; platform_machine != "s390x" and platform_machine != "ppc64le"
Requires-Dist: opentelemetry-sdk
Requires-Dist: packaging (>=25.0,<26.0)
Requires-Dist: pkce (>=1.0.3,<2.0.0)
Requires-Dist: pydantic (==1.8.2)
Requires-Dist: pyinstaller (>=5.12,<6.0)
Requires-Dist: requests (>=2.26.0,<3.0.0)
Requires-Dist: requests-oauthlib (>=2.0.0,<3.0.0)
Requires-Dist: retry (>=0.9.2,<0.10.0)
Requires-Dist: structlog (>=23.0.0,<24.0.0)
Requires-Dist: tenacity (>=8.0.1,<9.0.0)
Requires-Dist: urllib3 (>=1.26.0,<2.0.0)
Project-URL: Repository, https://github.com/10gen/db-contrib-tool
